<featureType>
  <id>FeatureTypeInfoImpl-72b1cc0:179ccb4a7d6:-63aa</id>
  <name>ind_or_population_1_sq_km</name>
  <nativeName>ind_or_population_1_sq_km</nativeName>
  <namespace>
    <id>NamespaceInfoImpl-53a0964:16fc2624139:-7ffe</id>
  </namespace>
  <title>ind_or_population_1_sq_km</title>
  <keywords>
    <string>features</string>
    <string>ind_or_population_1_sq_km</string>
  </keywords>
  <nativeCRS>GEOGCS[&quot;WGS 84&quot;, 
  DATUM[&quot;World Geodetic System 1984&quot;, 
    SPHEROID[&quot;WGS 84&quot;, 6378137.0, 298.257223563, AUTHORITY[&quot;EPSG&quot;,&quot;7030&quot;]], 
    AUTHORITY[&quot;EPSG&quot;,&quot;6326&quot;]], 
  PRIMEM[&quot;Greenwich&quot;, 0.0, AUTHORITY[&quot;EPSG&quot;,&quot;8901&quot;]], 
  UNIT[&quot;degree&quot;, 0.017453292519943295], 
  AXIS[&quot;Geodetic longitude&quot;, EAST], 
  AXIS[&quot;Geodetic latitude&quot;, NORTH], 
  AUTHORITY[&quot;EPSG&quot;,&quot;4326&quot;]]</nativeCRS>
  <srs>EPSG:4326</srs>
  <nativeBoundingBox>
    <minx>81.39031599527777</minx>
    <maxx>87.49917342166665</maxx>
    <miny>17.81135169694444</miny>
    <maxy>22.55937853361111</maxy>
    <crs>EPSG:4326</crs>
  </nativeBoundingBox>
  <latLonBoundingBox>
    <minx>81.39031599527777</minx>
    <maxx>87.49917342166665</maxx>
    <miny>17.81135169694444</miny>
    <maxy>22.55937853361111</maxy>
    <crs>EPSG:4326</crs>
  </latLonBoundingBox>
  <projectionPolicy>FORCE_DECLARED</projectionPolicy>
  <enabled>true</enabled>
  <metadata>
    <entry key="cachingEnabled">false</entry>
  </metadata>
  <store class="dataStore">
    <id>DataStoreInfoImpl-72b1cc0:179ccb4a7d6:-63ad</id>
  </store>
  <serviceConfiguration>false</serviceConfiguration>
  <simpleConversionEnabled>false</simpleConversionEnabled>
  <maxFeatures>0</maxFeatures>
  <numDecimals>0</numDecimals>
  <padWithZeros>false</padWithZeros>
  <forcedDecimal>false</forcedDecimal>
  <overridingServiceSRS>false</overridingServiceSRS>
  <skipNumberMatched>false</skipNumberMatched>
  <circularArcPresent>false</circularArcPresent>
</featureType>